[
    {
        "id":1,
        "category":"meals",
        "title":"Ana Yemek-1",
        "description":"Lorem ipsum dolor sit amet consectetur adipisicing elit. Ex animi dicta voluptate saepe? Eligendi labore deleniti nesciunt natus cum doloremque nostrum exercitationem libero, aliquid ratione in nobis obcaecati, corporis nemo.",
        "price":100,
        "ingredients":"Lorem ipsum dolor sit amet consectetur adipisicing elit.",
        "src":"images/food_images/317746397_142269145265182_1520541733806703493_n.jpg"
    },
    {
        "id":2,
        "category":"meals",
        "title":"Ana Yemek-2",
        "description":"Lorem ipsum dolor sit amet consectetur adipisicing elit. Ex animi dicta voluptate saepe? Eligendi labore deleniti nesciunt natus cum doloremque nostrum exercitationem libero, aliquid ratione in nobis obcaecati, corporis nemo.",
        "price":100,
        "ingredients":"Lorem ipsum dolor sit amet consectetur adipisicing elit.",
        "src":"images/food_images/337150018_123524983975439_7588435271802245678_n.jpg"
    },
    {
        "id":3,
        "category":"meals",
        "title":"Ana Yemek-3",
        "description":"Lorem ipsum dolor sit amet consectetur adipisicing elit. Ex animi dicta voluptate saepe? Eligendi labore deleniti nesciunt natus cum doloremque nostrum exercitationem libero, aliquid ratione in nobis obcaecati, corporis nemo.",
        "price":100,
        "ingredients":"Lorem ipsum dolor sit amet consectetur adipisicing elit.",
        "src":"images/food_images/353036062_233631482795614_6721860875268771354_n.jpg"
    },
    {
        "id":4,
        "category":"meals",
        "title":"Ana Yemek-4",
        "description":"Lorem ipsum dolor sit amet consectetur adipisicing elit. Ex animi dicta voluptate saepe? Eligendi labore deleniti nesciunt natus cum doloremque nostrum exercitationem libero, aliquid ratione in nobis obcaecati, corporis nemo.",
        "price":100,
        "ingredients":"Lorem ipsum dolor sit amet consectetur adipisicing elit.",
        "src":"images/food_images/353036062_233631482795614_6721860875268771354_n.jpg"
    },
    {
        "id":5,
        "category":"meals",
        "title":"Ana Yemek-5",
        "description":"Lorem ipsum dolor sit amet consectetur adipisicing elit. Ex animi dicta voluptate saepe? Eligendi labore deleniti nesciunt natus cum doloremque nostrum exercitationem libero, aliquid ratione in nobis obcaecati, corporis nemo.",
        "price":100,
        "ingredients":"Lorem ipsum dolor sit amet consectetur adipisicing elit.",
        "src":"images/food_images/353036062_233631482795614_6721860875268771354_n.jpg"
    },
    {
        "id":6,
        "category":"meals",
        "title":"Ana Yemek-6",
        "description":"Lorem ipsum dolor sit amet consectetur adipisicing elit. Ex animi dicta voluptate saepe? Eligendi labore deleniti nesciunt natus cum doloremque nostrum exercitationem libero, aliquid ratione in nobis obcaecati, corporis nemo.",
        "price":100,
        "ingredients":"Lorem ipsum dolor sit amet consectetur adipisicing elit.",
        "src":"images/food_images/353036062_233631482795614_6721860875268771354_n.jpg"
    },
    {
        "id":7,
        "category":"meals",
        "title":"Ana Yemek-7",
        "description":"Lorem ipsum dolor sit amet consectetur adipisicing elit. Ex animi dicta voluptate saepe? Eligendi labore deleniti nesciunt natus cum doloremque nostrum exercitationem libero, aliquid ratione in nobis obcaecati, corporis nemo.",
        "price":100,
        "ingredients":"Lorem ipsum dolor sit amet consectetur adipisicing elit.",
        "src":"images/food_images/353036062_233631482795614_6721860875268771354_n.jpg"
    },
    {
        "id":8,
        "category":"meals",
        "title":"Ana Yemek-8",
        "description":"Lorem ipsum dolor sit amet consectetur adipisicing elit. Ex animi dicta voluptate saepe? Eligendi labore deleniti nesciunt natus cum doloremque nostrum exercitationem libero, aliquid ratione in nobis obcaecati, corporis nemo.",
        "price":100,
        "ingredients":"Lorem ipsum dolor sit amet consectetur adipisicing elit.",
        "src":"images/food_images/353036062_233631482795614_6721860875268771354_n.jpg"
    },
    {
        "id":9,
        "category":"meals",
        "title":"Ana Yemek-9",
        "description":"Lorem ipsum dolor sit amet consectetur adipisicing elit. Ex animi dicta voluptate saepe? Eligendi labore deleniti nesciunt natus cum doloremque nostrum exercitationem libero, aliquid ratione in nobis obcaecati, corporis nemo.",
        "price":100,
        "ingredients":"Lorem ipsum dolor sit amet consectetur adipisicing elit.",
        "src":"images/food_images/353036062_233631482795614_6721860875268771354_n.jpg"
    },
    {
        "id":10,
        "category":"drinks",
        "title":"İçecek-1",
        "description":"Lorem ipsum dolor sit amet consectetur adipisicing elit. Ex animi dicta voluptate saepe? Eligendi labore deleniti nesciunt natus cum doloremque nostrum exercitationem libero, aliquid ratione in nobis obcaecati, corporis nemo.",
        "price":100,
        "ingredients":"Lorem ipsum dolor sit amet consectetur adipisicing elit.",
        "src":"images/food_images/353036062_233631482795614_6721860875268771354_n.jpg"
    },
    {
        "id":11,
        "category":"drinks",
        "title":"İçecek-2",
        "description":"Lorem ipsum dolor sit amet consectetur adipisicing elit. Ex animi dicta voluptate saepe? Eligendi labore deleniti nesciunt natus cum doloremque nostrum exercitationem libero, aliquid ratione in nobis obcaecati, corporis nemo.",
        "price":100,
        "ingredients":"Lorem ipsum dolor sit amet consectetur adipisicing elit.",
        "src":"images/food_images/353036062_233631482795614_6721860875268771354_n.jpg"
    },
    {
        "id":12,
        "category":"deserts",
        "title":"Tatlı-1",
        "description":"Lorem ipsum dolor sit amet consectetur adipisicing elit. Ex animi dicta voluptate saepe? Eligendi labore deleniti nesciunt natus cum doloremque nostrum exercitationem libero, aliquid ratione in nobis obcaecati, corporis nemo.",
        "price":100,
        "ingredients":"Lorem ipsum dolor sit amet consectetur adipisicing elit.",
        "src":"images/food_images/353036062_233631482795614_6721860875268771354_n.jpg"
    },
    {
        "id":13,
        "category":"deserts",
        "title":"Tatlı-2",
        "description":"Lorem ipsum dolor sit amet consectetur adipisicing elit. Ex animi dicta voluptate saepe? Eligendi labore deleniti nesciunt natus cum doloremque nostrum exercitationem libero, aliquid ratione in nobis obcaecati, corporis nemo.",
        "price":100,
        "ingredients":"Lorem ipsum dolor sit amet consectetur adipisicing elit.",
        "src":"images/food_images/353036062_233631482795614_6721860875268771354_n.jpg"
    }
]